HomOpt/HomM.py
HomOpt/__init__.py
homopt-0.2.0.dist-info/licenses/LICENSE
homopt-0.2.0.dist-info/METADATA
homopt-0.2.0.dist-info/WHEEL
homopt-0.2.0.dist-info/top_level.txt
homopt-0.2.0.dist-info/RECORD
